<AstroObjectEntry xmlns:xsi="http://www.w3.org/2001/XMLSchema-instance" xsi:noNamespaceSchemaLocation="https://raw.githubusercontent.com/Outer-Wilds-New-Horizons/new-horizons/main/NewHorizons/Schemas/shiplog_schema.xsd">
    <ID>Inspired</ID>


<Entry>
        <ID>INSPIRED</ID>
        <Name>The Inspired</Name>
        <Curiosity>STOWAWAYS</Curiosity>
        
        <IgnoreMoreToExplore/>

         <RumorFact>
            <ID>INSP R1</ID>
            <Text>I found a frozen comet hidden in the shadow of Giant's Deep.</Text>
        </RumorFact>
           <RumorFact>
            <ID>INSP R2</ID>
            <Text>I entered a black hole at the center of the comet. I was warped into a space with glowing masks, filled with ghost matter.</Text>
        </RumorFact>
          <RumorFact>
            <ID>INSP R3</ID>
               <SourceID>COMET_INTERIOR</SourceID>
            <Text>The Inspired was constructed in the Interloper's image.</Text>
        </RumorFact>
          <RumorFact>
            <ID>INSP R4</ID>
               <SourceID>DEEP_STORM_STATION</SourceID>
            <Text>The ghost matter collected by the Inspired was warped into the Deep Storm Station for containment.</Text>
        </RumorFact>
            <RumorFact>
            <ID>INSP R5</ID>
               <SourceID>DEEP_STORM_STATION</SourceID>
            <Text>The Inspired was made to bring destruction to the source of ghost matter.</Text>
        </RumorFact>

        <ExploreFact>
            <ID>INSP EX1</ID> 
            <Text>An artificial comet made of gravity crystals, made to bring destruction to the source of the Interloper.</Text> 
        </ExploreFact>
         <ExploreFact>
            <ID>INSP EX2</ID> 
            <Text>The Inspired was repurposed to protect the Hearthians when its creator realized that they were endangered by ghost matter.</Text>
        </ExploreFact>
         <ExploreFact>
            <ID>INSP EX3</ID> 
            <Text>The Inspired's warp core was replaced, allowing it to warp all collected ghost matter to the Deep Storm Station for containment.</Text>
        </ExploreFact>
      
</Entry>






</AstroObjectEntry>